hellojeno/__init__.py
hellojeno/jeno.py
hellojeno-0.0.6.dist-info/LICENSE.txt
hellojeno-0.0.6.dist-info/METADATA
hellojeno-0.0.6.dist-info/WHEEL
hellojeno-0.0.6.dist-info/top_level.txt
hellojeno-0.0.6.dist-info/RECORD
